AUTHOR
LICENSE
MANIFEST.in
README.rst
setup.cfg
setup.py
blizzard/__init__.py
blizzard/elasticfs.py
blizzard/info.py
doc/source/_static/blizzard.png
doc/source/_static/carousel/data1.png
doc/source/_static/carousel/data2.png
doc/source/_static/carousel/data3.png
doc/source/_static/carousel/data4.png
doc/source/_static/carousel/data5.png
doc/source/_static/carousel/hcp.png
doc/source/_static/carousel/ukb.png
python_blizzard.egg-info/PKG-INFO
python_blizzard.egg-info/SOURCES.txt
python_blizzard.egg-info/dependency_links.txt
python_blizzard.egg-info/requires.txt
python_blizzard.egg-info/top_level.txt