Metadata-Version: 1.1
Name: python-blizzard
Version: 1.0.1
Summary: 
